satgate/__init__.py
satgate/client.py
satgate/langchain_integrations.py
satgate-0.3.0.dist-info/METADATA
satgate-0.3.0.dist-info/WHEEL
satgate-0.3.0.dist-info/top_level.txt
satgate-0.3.0.dist-info/RECORD
