Metadata-Version: 2.4
Name: satgate
Version: 0.3.0
Summary: Python SDK for SatGate - Automatic L402 payments for AI Agents. The Stripe Moment.
Home-page: https://github.com/SatGate-io/satgate
Author: SatGate Team
Author-email: contact@satgate.io
Project-URL: Homepage, https://satgate.io
Project-URL: Documentation, https://satgate.io/playground
Project-URL: Repository, https://github.com/SatGate-io/satgate
Keywords: l402 lightning bitcoin micropayments api ai agents langchain openai gpt
Classifier: Development Status :: 4 - Beta
Classifier: Intended Audience :: Developers
Classifier: License :: OSI Approved :: MIT License
Classifier: Programming Language :: Python :: 3
Classifier: Programming Language :: Python :: 3.8
Classifier: Programming Language :: Python :: 3.9
Classifier: Programming Language :: Python :: 3.10
Classifier: Programming Language :: Python :: 3.11
Classifier: Programming Language :: Python :: 3.12
Classifier: Topic :: Internet :: WWW/HTTP
Classifier: Topic :: Software Development :: Libraries :: Python Modules
Classifier: Topic :: Scientific/Engineering :: Artificial Intelligence
Requires-Python: >=3.8
Requires-Dist: requests>=2.25.0
Provides-Extra: langchain
Requires-Dist: langchain>=0.1.0; extra == "langchain"
Requires-Dist: langchain-core>=0.1.0; extra == "langchain"
Requires-Dist: pydantic>=2.0.0; extra == "langchain"
Provides-Extra: openai
Requires-Dist: langchain>=0.1.0; extra == "openai"
Requires-Dist: langchain-openai>=0.0.5; extra == "openai"
Requires-Dist: pydantic>=2.0.0; extra == "openai"
Provides-Extra: dev
Requires-Dist: pytest; extra == "dev"
Requires-Dist: responses; extra == "dev"
Requires-Dist: flask; extra == "dev"
Dynamic: author
Dynamic: author-email
Dynamic: classifier
Dynamic: description
Dynamic: description-content-type
Dynamic: home-page
Dynamic: keywords
Dynamic: project-url
Dynamic: provides-extra
Dynamic: requires-dist
Dynamic: requires-python
Dynamic: summary
